{"expireTime":9007200865403555000,"key":"3d17db65dfc432f75a71d672a023240f","val":{"name":"IMAGE_PROCESSING","inputPaths":["/Users/dickflowers/Desktop/deploy/content/images/icons/5.png"],"outputDir":"/Users/dickflowers/Desktop/deploy/public/static/ee0f2ee1da7023a95bdaec5dcc8fb4fc","args":{"isLazy":false,"operations":[{"outputPath":"3f53f/5.png","args":{"width":25,"cropFocus":17,"toFormat":"png","fit":"cover","background":"rgba(0,0,0,1)"}},{"outputPath":"ef958/5.png","args":{"width":50,"cropFocus":17,"toFormat":"png","fit":"cover","background":"rgba(0,0,0,1)"}},{"outputPath":"65e33/5.png","args":{"width":100,"cropFocus":17,"toFormat":"png","fit":"cover","background":"rgba(0,0,0,1)"}},{"outputPath":"6d161/5.png","args":{"width":150,"cropFocus":17,"toFormat":"png","fit":"cover","background":"rgba(0,0,0,1)"}},{"outputPath":"69585/5.png","args":{"width":200,"cropFocus":17,"toFormat":"png","fit":"cover","background":"rgba(0,0,0,1)"}},{"outputPath":"ebd55/5.png","args":{"width":287,"cropFocus":17,"toFormat":"png","fit":"cover","background":"rgba(0,0,0,1)"}}],"pluginOptions":{"base64Width":20,"forceBase64Format":"","useMozJpeg":false,"stripMetadata":true,"lazyImageGeneration":true,"defaultQuality":50,"failOnError":true,"plugins":[]}}}}